Prometer/Prometer.py
Prometer/__init__.py
Prometer-0.1.3.dist-info/LICENSE
Prometer-0.1.3.dist-info/METADATA
Prometer-0.1.3.dist-info/WHEEL
Prometer-0.1.3.dist-info/top_level.txt
Prometer-0.1.3.dist-info/RECORD
