Metadata-Version: 2.1
Name: Prometer
Version: 0.1.3
Summary: Measuring Programmer Performance using some metrics from GitHub
Home-page: https://github.com/Susi-Eva/Prometer
Author: Susi Eva
Author-email: susipurba2@gmail.com
License: MIT
Keywords: Programmer,Measuring,GitHub
Platform: UNKNOWN
